Metadata-Version: 2.4
Name: perftrace
Version: 1.0.0
Summary: A lightweight Python profiler for tracing CPU, memory, I/O, GC, and system metrics with storage and CLI support.
Author-email: Maharavan <90346511+Maharavan@users.noreply.github.com>
License: MIT
Project-URL: Homepage, https://github.com/Maharavan/PerfTrace
Project-URL: Source, https://github.com/Maharavan/PerfTrace
Project-URL: Issues, https://github.com/Maharavan/PerfTrace/issues
Project-URL: Documentation, https://github.com/Maharavan/PerfTrace#readme
Classifier: Programming Language :: Python :: 3
Classifier: Programming Language :: Python :: 3.11
Classifier: Programming Language :: Python :: 3.12
Classifier: License :: OSI Approved :: MIT License
Classifier: Operating System :: OS Independent
Classifier: Topic :: System :: Monitoring
Classifier: Topic :: Software Development :: Testing
Requires-Python: >=3.11
License-File: LICENSE
Requires-Dist: click
Requires-Dist: rich
Requires-Dist: pandas
Requires-Dist: numpy
Requires-Dist: psycopg2-binary
Requires-Dist: duckdb
Requires-Dist: psutil
Requires-Dist: flatten_json
Requires-Dist: PyYAML
Dynamic: license-file
